LbScriptsLegacy/__init__.py
LbScriptsLegacy-0.1.2.dist-info/METADATA
LbScriptsLegacy-0.1.2.dist-info/RECORD
LbScriptsLegacy-0.1.2.dist-info/WHEEL
LbScriptsLegacy-0.1.2.dist-info/dependency_links.txt
LbScriptsLegacy-0.1.2.dist-info/entry_points.txt
LbScriptsLegacy-0.1.2.dist-info/top_level.txt
LbScriptsLegacy-0.1.2.dist-info/zip-safe
