Metadata-Version: 2.1
Name: LbScriptsLegacy
Version: 0.1.2
Summary: Legacy commands and tools from LbScripts, to be removed in the future
Home-page: https://gitlab.cern.ch/lhcb-core/LbScriptsLegacy
Author: CERN - LHCb Core Software
Author-email: lhcb-core-soft@cern.ch
License: UNKNOWN
Platform: UNKNOWN
Classifier: Development Status :: 4 - Beta
Classifier: Intended Audience :: Developers
Classifier: Topic :: Software Development :: Build Tools
Classifier: License :: OSI Approved :: GNU General Public License v3 or later (GPLv3+)
Classifier: Programming Language :: Python :: 2
Classifier: Programming Language :: Python :: 2.7
Classifier: Programming Language :: Python :: 3
Classifier: Programming Language :: Python :: 3.4
Classifier: Programming Language :: Python :: 3.5
Classifier: Programming Language :: Python :: 3.6
Classifier: Programming Language :: Python :: 3.7
Requires-Dist: LbDevTools
Requires-Dist: LbNightlyTools
